{
  "id": "setup_20_contrarian_bull_fails",
  "profile": "contrarian_bullish_falla",
  "symbol": "LINKUSDT",
  "timeframe": "4h",
  "decision_ts": "2022-03-02T16:00:00",
  "exit_ts": "2022-03-04T16:00:00",
  "entry_price": 15.261,
  "exit_price": 13.744,
  "outcome_pct": -9.94,
  "signals": {
    "trend_direction": {
      "state": "bullish_strong",
      "confidence": "strong",
      "detail": {
        "slope_pct_per_candle": 0.6958,
        "lookback": 20
      }
    },
    "recent_momentum": {
      "state": "mixed",
      "confidence": "moderate",
      "detail": {
        "bullish_candles": 2,
        "bearish_candles": 3,
        "body_ratio_vs_hist": 0.99,
        "body_trend": "rising"
      }
    },
    "volume_relative": {
      "state": "normal",
      "confidence": "moderate",
      "detail": {
        "ratio": 1.05,
        "recent_avg": 3689809.7600000002,
        "hist_avg": 3498338.9900000007
      }
    },
    "price_vs_ma25": {
      "state": "above",
      "confidence": "strong",
      "detail": {
        "z_score": 1.49,
        "pct_distance": 3.73
      }
    },
    "ma_cross_7_25": {
      "state": "ma7_above_stable",
      "confidence": "moderate",
      "detail": {
        "bars_since_cross": null,
        "lookback": 10
      }
    },
    "rsi_zone": {
      "state": "neutral_high",
      "confidence": "weak",
      "detail": {
        "rsi_value": 57.0
      }
    },
    "support_resistance": {
      "state": "mid_range",
      "confidence": "weak",
      "detail": {
        "high": 15.865,
        "low": 11.388,
        "position": 0.87
      }
    }
  },
  "bias": {
    "direction": "bullish",
    "strength": "strong"
  },
  "outcome": {
    "direction": "down",
    "pct_change": -9.94,
    "whipsaw": false
  },
  "edu_score": 85,
  "coherence": "contrarian",
  "pedagogical_notes": {
    "tooltip": {
      "es": "Tendencia alcista, pero contexto se agota.",
      "en": "Uptrend, but context wearing thin.",
      "zh": "趋势上涨,但背景正在耗尽。"
    },
    "holistic": {
      "es": "Señal alcista superficial, el fondo cedió. El precio cayó -9.94%.",
      "en": "Surface bullish signal, underlying gave. Price fell -9.94%.",
      "zh": "表面看涨,但基础让步。价格下跌 -9.94%。"
    }
  }
}