[
  {
    "symbol": "BTCUSDT",
    "timeframe": "1h",
    "start_ts": "2025-08-04T12:00:00",
    "decision_ts": "2025-08-10T14:00:00",
    "exit_ts": "2025-08-11T02:00:00",
    "entry_price": 118749.3,
    "exit_price": 121837.5,
    "sig_trend_direction": "bullish",
    "sig_recent_momentum": "mixed",
    "sig_volume_relative": "normal",
    "sig_price_vs_ma25": "far_above",
    "sig_ma_cross_7_25": "ma7_above_stable",
    "sig_rsi_zone": "neutral_high",
    "sig_support_resistance": "breaking_resistance",
    "bias_score": 6,
    "bias_direction": "bullish",
    "bias_strength": "strong",
    "outcome_direction": "up",
    "outcome_pct": 2.6,
    "outcome_whipsaw": false,
    "edu_score": 90,
    "coherence": "confirmed",
    "signals_full": {
      "trend_direction": {
        "state": "bullish",
        "detail": {
          "slope_pct_per_candle": 0.1076,
          "lookback": 20
        },
        "confidence": "moderate"
      },
      "recent_momentum": {
        "state": "mixed",
        "detail": {
          "bullish_candles": 3,
          "bearish_candles": 2,
          "body_ratio_vs_hist": 0.97,
          "body_trend": "falling"
        },
        "confidence": "moderate"
      },
      "volume_relative": {
        "state": "normal",
        "detail": {
          "ratio": 0.91,
          "recent_avg": 4510.8778999999995,
          "hist_avg": 4936.419355000001
        },
        "confidence": "moderate"
      },
      "price_vs_ma25": {
        "state": "far_above",
        "detail": {
          "z_score": 2.19,
          "pct_distance": 1.12
        },
        "confidence": "strong"
      },
      "ma_cross_7_25": {
        "state": "ma7_above_stable",
        "detail": {
          "bars_since_cross": null,
          "lookback": 10
        },
        "confidence": "moderate"
      },
      "rsi_zone": {
        "state": "neutral_high",
        "detail": {
          "rsi_value": 67.6
        },
        "confidence": "moderate"
      },
      "support_resistance": {
        "state": "breaking_resistance",
        "detail": {
          "high": 118841.7,
          "low": 115850.0,
          "position": 0.97
        },
        "confidence": "strong"
      }
    }
  },
  {
    "symbol": "BTCUSDT",
    "timeframe": "1h",
    "start_ts": "2022-06-13T12:00:00",
    "decision_ts": "2022-06-19T14:00:00",
    "exit_ts": "2022-06-20T02:00:00",
    "entry_price": 19460.0,
    "exit_price": 19936.301,
    "sig_trend_direction": "bullish_strong",
    "sig_recent_momentum": "mixed",
    "sig_volume_relative": "normal",
    "sig_price_vs_ma25": "above",
    "sig_ma_cross_7_25": "fresh_bullish_cross",
    "sig_rsi_zone": "neutral_high",
    "sig_support_resistance": "mid_range",
    "bias_score": 6,
    "bias_direction": "bullish",
    "bias_strength": "strong",
    "outcome_direction": "up",
    "outcome_pct": 2.45,
    "outcome_whipsaw": false,
    "edu_score": 90,
    "coherence": "confirmed",
    "signals_full": {
      "trend_direction": {
        "state": "bullish_strong",
        "detail": {
          "slope_pct_per_candle": 0.3212,
          "lookback": 20
        },
        "confidence": "strong"
      },
      "recent_momentum": {
        "state": "mixed",
        "detail": {
          "bullish_candles": 2,
          "bearish_candles": 3,
          "body_ratio_vs_hist": 1.49,
          "body_trend": "falling"
        },
        "confidence": "moderate"
      },
      "volume_relative": {
        "state": "normal",
        "detail": {
          "ratio": 1.07,
          "recent_avg": 58892.174399999996,
          "hist_avg": 55056.38215
        },
        "confidence": "moderate"
      },
      "price_vs_ma25": {
        "state": "above",
        "detail": {
          "z_score": 0.95,
          "pct_distance": 3.81
        },
        "confidence": "moderate"
      },
      "ma_cross_7_25": {
        "state": "fresh_bullish_cross",
        "detail": {
          "bars_since_cross": "3",
          "lookback": 10
        },
        "confidence": "strong"
      },
      "rsi_zone": {
        "state": "neutral_high",
        "detail": {
          "rsi_value": 55.6
        },
        "confidence": "weak"
      },
      "support_resistance": {
        "state": "mid_range",
        "detail": {
          "high": 20912.4,
          "low": 17593.199,
          "position": 0.56
        },
        "confidence": "weak"
      }
    }
  },
  {
    "symbol": "BTCUSDT",
    "timeframe": "1h",
    "start_ts": "2021-06-01T18:00:00",
    "decision_ts": "2021-06-07T20:00:00",
    "exit_ts": "2021-06-08T08:00:00",
    "entry_price": 34431.109,
    "exit_price": 32891.34,
    "sig_trend_direction": "bearish_strong",
    "sig_recent_momentum": "accelerating_down",
    "sig_volume_relative": "rising",
    "sig_price_vs_ma25": "far_below",
    "sig_ma_cross_7_25": "fresh_bearish_cross",
    "sig_rsi_zone": "oversold",
    "sig_support_resistance": "mid_range",
    "bias_score": -6,
    "bias_direction": "bearish",
    "bias_strength": "strong",
    "outcome_direction": "down",
    "outcome_pct": -4.47,
    "outcome_whipsaw": false,
    "edu_score": 90,
    "coherence": "confirmed",
    "signals_full": {
      "trend_direction": {
        "state": "bearish_strong",
        "detail": {
          "slope_pct_per_candle": -0.1761,
          "lookback": 20
        },
        "confidence": "strong"
      },
      "recent_momentum": {
        "state": "accelerating_down",
        "detail": {
          "bullish_candles": 1,
          "bearish_candles": 4,
          "body_ratio_vs_hist": 1.96,
          "body_trend": "rising"
        },
        "confidence": "strong"
      },
      "volume_relative": {
        "state": "rising",
        "detail": {
          "ratio": 1.51,
          "recent_avg": 31917.188199999997,
          "hist_avg": 21104.220305000003
        },
        "confidence": "moderate"
      },
      "price_vs_ma25": {
        "state": "far_below",
        "detail": {
          "z_score": -3.75,
          "pct_distance": -4.52
        },
        "confidence": "strong"
      },
      "ma_cross_7_25": {
        "state": "fresh_bearish_cross",
        "detail": {
          "bars_since_cross": "3",
          "lookback": 10
        },
        "confidence": "strong"
      },
      "rsi_zone": {
        "state": "oversold",
        "detail": {
          "rsi_value": 26.9
        },
        "confidence": "moderate"
      },
      "support_resistance": {
        "state": "mid_range",
        "detail": {
          "high": 36820.0,
          "low": 33910.0,
          "position": 0.18
        },
        "confidence": "weak"
      }
    }
  },
  {
    "symbol": "BTCUSDT",
    "timeframe": "1h",
    "start_ts": "2022-06-12T06:00:00",
    "decision_ts": "2022-06-18T08:00:00",
    "exit_ts": "2022-06-18T20:00:00",
    "entry_price": 18997.6,
    "exit_price": 17798.0,
    "sig_trend_direction": "bearish_strong",
    "sig_recent_momentum": "accelerating_down",
    "sig_volume_relative": "rising",
    "sig_price_vs_ma25": "far_below",
    "sig_ma_cross_7_25": "ma7_below_stable",
    "sig_rsi_zone": "oversold",
    "sig_support_resistance": "mid_range",
    "bias_score": -5,
    "bias_direction": "bearish",
    "bias_strength": "strong",
    "outcome_direction": "down",
    "outcome_pct": -6.31,
    "outcome_whipsaw": false,
    "edu_score": 90,
    "coherence": "confirmed",
    "signals_full": {
      "trend_direction": {
        "state": "bearish_strong",
        "detail": {
          "slope_pct_per_candle": -0.2947,
          "lookback": 20
        },
        "confidence": "strong"
      },
      "recent_momentum": {
        "state": "accelerating_down",
        "detail": {
          "bullish_candles": 1,
          "bearish_candles": 4,
          "body_ratio_vs_hist": 2.8,
          "body_trend": "rising"
        },
        "confidence": "strong"
      },
      "volume_relative": {
        "state": "rising",
        "detail": {
          "ratio": 2.39,
          "recent_avg": 65443.1777,
          "hist_avg": 27403.448450000004
        },
        "confidence": "strong"
      },
      "price_vs_ma25": {
        "state": "far_below",
        "detail": {
          "z_score": -3.57,
          "pct_distance": -7.13
        },
        "confidence": "strong"
      },
      "ma_cross_7_25": {
        "state": "ma7_below_stable",
        "detail": {
          "bars_since_cross": null,
          "lookback": 10
        },
        "confidence": "moderate"
      },
      "rsi_zone": {
        "state": "oversold",
        "detail": {
          "rsi_value": 20.7
        },
        "confidence": "strong"
      },
      "support_resistance": {
        "state": "mid_range",
        "detail": {
          "high": 21928.699,
          "low": 18690.0,
          "position": 0.09
        },
        "confidence": "weak"
      }
    }
  }
]